{
    "$schema": "https://schema.management.azure.com/schemas/2015-01-01/deploymentParameters.json#",
    "contentVersion": "1.0.0.0",
    "parameters": {
        "location": {
            "value": "southcentralus"
        },
        "virtualMachineName": {
            "value": "demo-azblockchain-hlf"
        },
        "virtualMachineSize": {
            "value": "Standard_DS2_v2"
        },
        "adminUsername": {
            "value": "azureuser"
        },
        "virtualNetworkName": {
            "value": "azblockchain-vnet"
        },
        "networkInterfaceName": {
            "value": "demo-azblockchain-hl524"
        },
        "networkSecurityGroupName": {
            "value": "demoazblockchainhlf910-nsg"
        },
        "adminPassword": {
            "value": null
        },
        "subnetName": {
            "value": "default"
        },
        "publicIpAddressName": {
            "value": "demoazblockchainhlf827"
        },
        "publicIpAddressType": {
            "value": "Dynamic"
        },
        "publicIpAddressSku": {
            "value": "Basic"
        }
    }
}